Turtle3D.py
turtle3D-0.1.dist-info/LICENSE
turtle3D-0.1.dist-info/METADATA
turtle3D-0.1.dist-info/WHEEL
turtle3D-0.1.dist-info/top_level.txt
turtle3D-0.1.dist-info/RECORD
